{
  "atm_strike": 7245.0,
  "atm_iv_pct": 7.0,
  "spot": 7245.14,
  "parity_estimates": [
    {
      "strike": 7235.0,
      "call_last": 12.74,
      "put_last": 2.37,
      "call_delta": 0.7736420028332184,
      "estimate": 7245.37
    },
    {
      "strike": 7240.0,
      "call_last": 8.2,
      "put_last": 3.2,
      "call_delta": 0.6543956593800211,
      "estimate": 7245.0
    },
    {
      "strike": 7245.0,
      "call_last": 5.2,
      "put_last": 5.1,
      "call_delta": 0.5024865464262258,
      "estimate": 7245.1
    },
    {
      "strike": 7250.0,
      "call_last": 2.9,
      "put_last": 7.7,
      "call_delta": 0.34840058298699306,
      "estimate": 7245.2
    },
    {
      "strike": 7255.0,
      "call_last": 1.65,
      "put_last": 11.6,
      "call_delta": 0.20649537805153204,
      "estimate": 7245.05
    }
  ],
  "primary_spot_source": "massive_index_1m_aggregate",
  "primary_spot": 7242.860000000001,
  "primary_spot_timestamp_et": "2026-05-01 14:30:00 ET",
  "parity_fallback_spot": 7245.14,
  "index_spot_raw": {
    "url": "https://api.massive.com/v2/aggs/ticker/I:SPX/range/1/minute/2026-04-28/2026-05-01",
    "params": {
      "adjusted": "true",
      "sort": "desc",
      "limit": 1
    },
    "result": {
      "o": 7244.92,
      "c": 7242.860000000001,
      "h": 7245.02,
      "l": 7242.71,
      "t": 1777660200000
    },
    "status": "DELAYED",
    "resultsCount": null
  }
}